{
  "$schema": "https://mintlify.com/schema.json",
  "name": "Maya Labs Docs",
  "logo": {
    "dark": "/logo/dark.png",
    "light": "/logo/light.png"
  },
  "favicon": "/favicon-32x32.png",
  "colors": {
    "primary": "#4f2f4d",
    "light": "#b681b3",
    "dark": "#4f2f4d"
  },
  "topbarLinks": [
    {
      "name": "Documentation",
      "url": "https://mayalabs.io/docs"
    }
  ],
  "topbarCtaButton": {
    "name": "Get Started",
    "url": "https://app.mayalabs.io"
  },
  "anchors": [
    {
      "name": "Changelog",
      "icon": "list",
      "url": "changelog"
    },
    {
      "name": "Support",
      "icon": "envelope",
      "url": "mailto:support@mayalabs.io"
    }
  ],
  "navigation": [
    {
      "group": "Overview",
      "pages": [
        "introduction",
        "tutorial",
        "capabilities"
      ]
    },
    {
      "group": "Examples",
      "pages": [
        "examples/conditionals",
        "examples/custom",
        "examples/web",
        "examples/repeating",
        "examples/dashboards",
        "examples/bots",
        "examples/pipelines",
        "examples/processes",
        "examples/memory",
        "examples/labour"
      ]
    },
    {
      "group": "Teaching",
      "pages": [
        "teaching/introduction",
        "teaching/steps"
      ]
    },
    {
      "group": "Changelog",
      "pages": [
        "changelog/log"
      ]
    }
  ],
  "footerSocials": {
    "twitter": "https://twitter.com/mayalabsio",
    "github": "https://github.com/mayahq"
  }
}